<?xml version="1.0" encoding="windows-1251" standalone="yes" ?>
<triggers>

    <trigger Name="PEREGREV_OUT" active="0">
		<event eventid="GE_OBJECT_LEAVES_LOCATION" ObjName="SaveZone_Port_loc" />
		<event eventid="GE_OBJECT_LEAVES_LOCATION" ObjName="SaveZone_Karier_loc" />
		<event eventid="GE_OBJECT_LEAVES_LOCATION" ObjName="SaveZone_Kochewnik_loc" />
		<event eventid="GE_OBJECT_LEAVES_LOCATION" ObjName="SaveZone_DerevnyaFRM_loc" />
		<event eventid="GE_OBJECT_LEAVES_LOCATION" ObjName="SaveZone_Citadel_loc" />
		<event eventid="GE_OBJECT_LEAVES_LOCATION" ObjName="SaveZone_Oplot_loc" />
		<event eventid="GE_OBJECT_LEAVES_LOCATION" ObjName="SaveZone_Garden_loc" />
		<event eventid="GE_OBJECT_LEAVES_LOCATION" ObjName="SaveZone_Neft_loc" />
		<script>
            TActivate("PEREGREV_BOOM_1")
			TActivate("PEREGREV_BOOM_2")
			TActivate("PEREGREV_BOOM_3")
			TActivate("PEREGREV_BOOM_4")
			TActivate("PEREGREV_BOOM_5")

			
			
		</script>
	</trigger>

	<trigger Name="PEREGREV_INTER" active="0">
		<event eventid="GE_OBJECT_ENTERS_LOCATION" ObjName="SaveZone_Port_loc" />
		<event eventid="GE_OBJECT_ENTERS_LOCATION" ObjName="SaveZone_Karier_loc" />
		<event eventid="GE_OBJECT_ENTERS_LOCATION" ObjName="SaveZone_Kochewnik_loc" />
		<event eventid="GE_OBJECT_ENTERS_LOCATION" ObjName="SaveZone_DerevnyaFRM_loc" />
		<event eventid="GE_OBJECT_ENTERS_LOCATION" ObjName="SaveZone_Citadel_loc" />
		<event eventid="GE_OBJECT_ENTERS_LOCATION" ObjName="SaveZone_Oplot_loc" />
		<event eventid="GE_OBJECT_ENTERS_LOCATION" ObjName="SaveZone_Garden_loc" />
		<event eventid="GE_OBJECT_ENTERS_LOCATION" ObjName="SaveZone_Neft_loc" />
		<script>
            AddImportantFadingMsgByStrIdFormatted( "fm_PEREGEV_11" )
			TDeactivate("PEREGREV_BOOM_1")
			TDeactivate("PEREGREV_BOOM_2")
			TDeactivate("PEREGREV_BOOM_3")
			TDeactivate("PEREGREV_BOOM_4")
			TDeactivate("PEREGREV_BOOM_5")
			TDeactivate("PEREGREVHEALTH")
			TDeactivate("PEREGREVHEALTH2")
			TActivate("PEREGREV_BOOM_6")
            
			StopPlayingCustomMusic()
			
            trigger:Deactivate()
 		</script>
	</trigger>

	<trigger Name="PEREGREV_BOOM_1" active="0">
		<event timeout="60" eventid="GE_TIME_PERIOD" />
		<script>
			AddImportantFadingMsgByStrIdFormatted( "fm_PEREGEV_1" )
			trigger:Deactivate()
		</script>
	</trigger>

	<trigger Name="PEREGREV_BOOM_2" active="0">
		<event timeout="120" eventid="GE_TIME_PERIOD" />
		<script>
			AddImportantFadingMsgByStrIdFormatted( "fm_PEREGEV_2" )
			trigger:Deactivate()
		</script>
	</trigger>

	<trigger Name="PEREGREV_BOOM_3" active="0">
		<event timeout="1.5" eventid="GE_TIME_PERIOD" />
		<script>
            god(0)
		    PlayCustomMusic("Passage02")
			AddImportantFadingMsgByStrIdFormatted( "fm_PEREGEV_3" )
			TActivate("PEREGREV_BOOM_4")
			TActivate("PEREGREV_BOOM_5")
			trigger:Deactivate()
		</script>
	</trigger>

	<trigger Name="PEREGREV_BOOM_4" active="0">
		<event timeout="30" eventid="GE_TIME_PERIOD" />
		<script>
			AddImportantFadingMsgByStrIdFormatted( "fm_PEREGEV_4" )
			TActivate("PEREGREVHEALTH")
            trigger:Deactivate()
		</script>
	</trigger>

	<trigger Name="PEREGREV_BOOM_5" active="0">
		<event timeout="50" eventid="GE_TIME_PERIOD" />
		<script>
			AddImportantFadingMsgByStrIdFormatted( "fm_PEREGEV_5" )
            TActivate("PEREGREVHEALTH2")
			TDeactivate("PEREGREVHEALTH")
			trigger:Deactivate()
		</script>
	</trigger>

	<trigger Name="PEREGREVHEALTH" active="0">
		<event timeout="0.5" eventid="GE_TIME_PERIOD" />
		<script>
			local vehPlayer = GetPlayerVehicle()
			if vehPlayer then       
				vehPlayer:AddModifier("hp","- 1")
			end

		</script>
	</trigger>

	<trigger Name="PEREGREVHEALTH2" active="0">
		<event timeout="0.05" eventid="GE_TIME_PERIOD" />
		<script>
			local vehPlayer = GetPlayerVehicle()
			if vehPlayer then       
				vehPlayer:AddModifier("hp","- 1")
			end

		</script>
	</trigger>

	<trigger Name="PEREGREV_BOOM_6" active="0">
		<event timeout="3" eventid="GE_TIME_PERIOD" />
		<script>
			AddImportantFadingMsgByStrIdFormatted( "fm_PEREGEV_22" )

			trigger:Deactivate()
		</script>
	</trigger>
	
    <trigger Name="VELIKOE_NI4TO" active="1">
		<event eventid="GE_OBJECT_LEAVES_LOCATION" ObjName="Nichto_loc" />
		<script>
			AddImportantFadingMsgByStrIdFormatted( "fm_NI4TO" )
            TActivate("Timer_BOOM_1")
			TActivate("Timer_BOOM")

			PlayCustomMusic("r4_2_alarm")
			
		</script>
	</trigger>

	<trigger Name="Timer_BOOM_1" active="0">
		<event timeout="0.1" eventid="GE_TIME_PERIOD" />
		<script>
			local vehPlayer = GetPlayerVehicle()
			if vehPlayer then       
				vehPlayer:AddModifier("hp","- 1")
			end

		</script>
	</trigger>

    <trigger Name="Timer_BOOM" active="0">
		<event timeout="5" eventid="GE_TIME_PERIOD" />
		<script>
			TActivate("Timer_BOOM_2")
            
			trigger:Deactivate()
		</script>
	</trigger>

	<trigger Name="Timer_BOOM_2" active="0">
		<event timeout="0.01" eventid="GE_TIME_PERIOD" />
		<script>
			local vehPlayer = GetPlayerVehicle()
			if vehPlayer then       
				vehPlayer:AddModifier("hp","- 1")
			end

            
		</script>
	</trigger>

    <trigger Name="VELIKOE_NI4TO_RETURN" active="1">
		<event eventid="GE_OBJECT_ENTERS_LOCATION" ObjName="Nichto_loc" />
		<script>

			TDeactivate("Timer_BOOM_1")
			TDeactivate("Timer_BOOM")
			TDeactivate("Timer_BOOM_2")

			StopPlayingCustomMusic()

 		</script>
	</trigger>

	<trigger Name="Create_gate" active="1">
		<event timeout="0" eventid="GE_TIME_PERIOD" />
		<script>
			CreateNewDummyObject( "kef_gate",	"VOROTA1", -1, -1, CVector(3730.653, 313.469, 4050.167), Quaternion(0.0000, 0.0000, 1.0000, -0.0000),1 )

			CreateNewBreakableObject( "heavy_dot2_rainmetal","dot19", 1024, CVector(3712.722, 314.774, 4026.041), Quaternion(0.000, 0.702, 0.000, 0.712),0 )
			CreateNewBreakableObject( "heavy_dot2_rainmetal","dot20", 1024, CVector(3713.212, 313.856, 4074.538), Quaternion(0.000, 0.707, 0.000, 0.707),0 )

			trigger:Deactivate()
		</script>
	</trigger>

	<trigger Name="Kochewnik_active" active="1">
		<event timeout="0" eventid="GE_TIME_PERIOD" />
		<script>
			
			CreateVehicleEx("CoolBelaz_3","Koch_1", CVector(2086.163, 282.301, 3861.111), 1064)

			local vehKoch1 = GetEntityByName("Koch_1")
			if vehKoch1 then
				vehKoch1:SetPosition( CVector(5955.514, 282.070, 1631.042))
				vehKoch1:SetRotation(Quaternion(-0.002, -0.868, 0.002, 0.497))
			end

			CreateNewSgNodeObject("ET_PS_HOUSE_MED_FIRE", "FireKoch1", -1, -1, CVector(5930.416, 280.000, 1620.900), Quaternion(0.0000, 0.0000, 0.0000, 1.0000), 0.205)

			trigger:Deactivate()
		</script>
	</trigger>

	<trigger Name="triggerExitToMap42" active="0">
		<event    eventid="GE_LEAVE_TOWN"    ObjName="r1m4_StorageVillage2302" />
		<script>
		    local FurrrrrryCCC1 = GetEntityByName("FuryCar112")
			if FurrrrrryCCC1 then FurrrrrryCCC1:Remove() end
			
			PassToMap("r4m2", "FromR4M1", -1 )

			

			TActivate("AfterRace_cin")
			trigger:Deactivate()
 		</script>
	</trigger>

	<trigger Name="RolikENDExitToMap42" active="0">
		<event eventid="GE_END_CINEMATIC" ObjName="Player1" />
		<event eventid="GE_SKIP_CINEMATIC" ObjName="Player1" />
		<script>
			GameFiltersUse()

			RestoreAllToleranceStatus()

			

			SetCameraBehindPlayerVehicle()

			trigger:Deactivate()
		</script>
	</trigger>

</triggers>

